setup.py
css/__init__.py
css/grammar.py
css.egg-info/PKG-INFO
css.egg-info/SOURCES.txt
css.egg-info/dependency_links.txt
css.egg-info/top_level.txt