Metadata-Version: 1.0
Name: css
Version: 0.1
Summary: a small, fast css parser for python the utilizes the codetalker library
Home-page: http://jaredforsyth.com/projects/css
Author: Jared Forsyth
Author-email: jared@jaredforsyth.com
License: UNKNOWN
Download-URL: http://github.com/jabapyth/css
Platform: UNKNOWN
Classifier: License :: OSI Approved :: MIT License
Classifier: Programming Language :: Python
